liketunicorn/__init__.py
liketunicorn/__main__.py
liketunicorn/config.py
liketunicorn/exceptions.py
liketunicorn/importer.py
liketunicorn/logger.py
liketunicorn/main.py
liketunicorn/polling.py
liketunicorn/protocol.py
liketunicorn/server.py
liketunicorn/enums/__init__.py
liketunicorn/enums/run_type.py
liketunicorn-2.0.1.dist-info/METADATA
liketunicorn-2.0.1.dist-info/WHEEL
liketunicorn-2.0.1.dist-info/licenses/LICENSE
liketunicorn-2.0.1.dist-info/RECORD
