Metadata-Version: 2.1
Name: liketunicorn
Version: 2.0.1
Summary: The runner for liketapi
Project-URL: Homepage, https://github.com/liketapi/liketunicorn
Project-URL: Bug Tracker, https://github.com/liketapi/liketunicorn/issues
Author-email: liketapi <seryumed@gmail.com>
License-File: LICENSE
Requires-Python: >=3.6
